real_time_asr/__init__.py
real_time_asr/asr.py
real_time_asr-0.1.0.dist-info/METADATA
real_time_asr-0.1.0.dist-info/WHEEL
real_time_asr-0.1.0.dist-info/top_level.txt
real_time_asr-0.1.0.dist-info/RECORD
