Metadata-Version: 2.1
Name: real_time_asr
Version: 0.1.0
Summary: Real-time ASR using Wav2Vec2 model with PyAudio
Author: Aditya Raj
Author-email: adityaraj0071506@gmail.com
Classifier: Programming Language :: Python :: 3
Classifier: License :: OSI Approved :: MIT License
Classifier: Operating System :: OS Independent
Requires-Python: >=3.6
Requires-Dist: pyaudio
Requires-Dist: torch
Requires-Dist: numpy
Requires-Dist: transformers
